concisely/__init__.py
concisely/apps.py
concisely/blocks.py
concisely/semantic_feature_names.py
concisely/semantic_features.py
concisely/wagtail_hooks.py
concisely/static/concisely/css/concisely.css
concisely/static/concisely/js/concisely.js
concisely/templates/concisely/blocks/begin_columns_block.html
concisely/templates/concisely/blocks/begin_flow_block.html
concisely/templates/concisely/blocks/column_break_block.html
concisely/templates/concisely/blocks/end_columns_block.html
concisely/templates/concisely/blocks/end_flow_block.html
concisely/templates/concisely/blocks/flow_break_block.html
concisely/templates/concisely/blocks/heading_block.html
concisely/templatetags/__init__.py
concisely/templatetags/concisely_tags.py
concisely-4.1.0.dist-info/AUTHORS.txt
concisely-4.1.0.dist-info/LICENSE.txt
concisely-4.1.0.dist-info/METADATA
concisely-4.1.0.dist-info/WHEEL
concisely-4.1.0.dist-info/top_level.txt
concisely-4.1.0.dist-info/zip-safe
concisely-4.1.0.dist-info/RECORD
